CHANGES.txt
MANIFEST.in
README.txt
setup.cfg
setup.py
freeboxtv/__init__.py
freeboxtv/app.py
freeboxtv/config.py
freeboxtv/player.py
freeboxtv/utils.py
freeboxtv.egg-info/PKG-INFO
freeboxtv.egg-info/SOURCES.txt
freeboxtv.egg-info/dependency_links.txt
freeboxtv.egg-info/entry_points.txt
freeboxtv.egg-info/not-zip-safe
freeboxtv.egg-info/requires.txt
freeboxtv.egg-info/top_level.txt
freeboxtv/views/browser.html
freeboxtv/views/cmd.html
freeboxtv/views/control.html
freeboxtv/views/footer.html
freeboxtv/views/header.html
freeboxtv/views/info.html
freeboxtv/views/settings.html