Metadata-Version: 1.0
Name: freeboxtv
Version: 0.9.1
Summary: VLC launcher for Freebox TV/Freeplayer
Home-page: https://github.com/gawel/freeboxtv
Author: Gael Pasgrimaud
Author-email: gael@gawel.org
License: GPL
Keywords: freebox
Platform: UNKNOWN
Classifier: Environment :: Console
Classifier: License :: OSI Approved
Classifier: Operating System :: POSIX
Classifier: Topic :: Home Automation
